[
  { "nome": "Hansa Yellow Medium PY97", "codice": "PY97", "colore": "#E8C100", "tipo": "trasparente", "opacita": 0.35, "k_factor": 1.0, "s_factor": 0.40, "resistenza_luce": "eccellente", "compatibilità": ["acrilico", "acquerello"], "indice_tintoriale": 8 },
  { "nome": "Cadmium Lemon PY35", "codice": "PY35", "colore": "#F5DD00", "tipo": "opaco", "opacita": 0.95, "k_factor": 1.0, "s_factor": 1.65, "resistenza_luce": "eccellente", "compatibilità": ["olio", "acrilico"], "indice_tintoriale": 6 },
  { "nome": "Cadmium Yellow Pale PY37", "codice": "PY37", "colore": "#F5E000", "tipo": "opaco", "opacita": 0.95, "k_factor": 1.0, "s_factor": 1.65, "resistenza_luce": "eccellente", "compatibilità": ["olio", "acrilico"], "indice_tintoriale": 6 },
  { "nome": "Cadmium Yellow Light PY35", "codice": "PY35b", "colore": "#E8A400", "tipo": "opaco", "opacita": 0.95, "k_factor": 1.0, "s_factor": 1.60, "resistenza_luce": "eccellente", "compatibilità": ["olio", "acrilico"], "indice_tintoriale": 6 },
  { "nome": "Naples Yellow PY35", "codice": "PY35c", "colore": "#F0D878", "tipo": "opaco", "opacita": 0.88, "k_factor": 1.0, "s_factor": 1.50, "resistenza_luce": "buona", "compatibilità": ["olio", "acrilico"], "indice_tintoriale": 4 },
  { "nome": "Benzimida Yellow PY151", "codice": "PY151", "colore": "#ECC800", "tipo": "trasparente", "opacita": 0.30, "k_factor": 1.0, "s_factor": 0.35, "resistenza_luce": "eccellente", "compatibilità": ["acrilico", "acquerello"], "indice_tintoriale": 7 },
  { "nome": "Nickel Azomethine Yellow PY150", "codice": "PY150", "colore": "#D8C000", "tipo": "trasparente", "opacita": 0.35, "k_factor": 1.0, "s_factor": 0.40, "resistenza_luce": "eccellente", "compatibilità": ["olio", "acrilico", "acquerello"], "indice_tintoriale": 7 },
  { "nome": "Antrapyrimidine Yellow PY108", "codice": "PY108", "colore": "#E8B800", "tipo": "trasparente", "opacita": 0.35, "k_factor": 1.0, "s_factor": 0.40, "resistenza_luce": "buona", "compatibilità": ["acrilico"], "indice_tintoriale": 8 },
  { "nome": "Hansa Yellow Deep PY65", "codice": "PY65", "colore": "#E8B400", "tipo": "trasparente", "opacita": 0.35, "k_factor": 1.0, "s_factor": 0.40, "resistenza_luce": "buona", "compatibilità": ["acrilico", "acquerello"], "indice_tintoriale": 8 },
  { "nome": "Gold Ochre PY42", "codice": "PY42", "colore": "#BA8020", "tipo": "opaco", "opacita": 0.85, "k_factor": 1.0, "s_factor": 1.40, "resistenza_luce": "eccellente", "compatibilità": ["olio", "acrilico", "acquerello"], "indice_tintoriale": 3 },
  { "nome": "Yellow Ochre PY43", "codice": "PY43", "colore": "#B08428", "tipo": "opaco", "opacita": 0.85, "k_factor": 1.0, "s_factor": 1.40, "resistenza_luce": "eccellente", "compatibilità": ["olio", "acrilico", "acquerello"], "indice_tintoriale": 3 },
  { "nome": "Olive Green PY43", "codice": "PY43b", "colore": "#6E6E28", "tipo": "opaco", "opacita": 0.85, "k_factor": 1.0, "s_factor": 1.30, "resistenza_luce": "eccellente", "compatibilità": ["olio", "acrilico"], "indice_tintoriale": 4 },
  { "nome": "Chrome Titanate PBr24", "codice": "PBr24", "colore": "#A87828", "tipo": "opaco", "opacita": 0.90, "k_factor": 1.0, "s_factor": 1.50, "resistenza_luce": "eccellente", "compatibilità": ["olio", "acrilico"], "indice_tintoriale": 5 },
  { "nome": "Cadmium Orange PO20", "codice": "PO20", "colore": "#D85020", "tipo": "opaco", "opacita": 0.95, "k_factor": 1.0, "s_factor": 1.60, "resistenza_luce": "eccellente", "compatibilità": ["olio", "acrilico"], "indice_tintoriale": 6 },
  { "nome": "Benzimida Orange PO62", "codice": "PO62", "colore": "#D04810", "tipo": "trasparente", "opacita": 0.30, "k_factor": 1.0, "s_factor": 0.35, "resistenza_luce": "buona", "compatibilità": ["acrilico", "acquerello"], "indice_tintoriale": 8 },
  { "nome": "Quinacridone Deep Gold PO49", "codice": "PO49", "colore": "#B86818", "tipo": "trasparente", "opacita": 0.30, "k_factor": 1.0, "s_factor": 0.30, "resistenza_luce": "eccellente", "compatibilità": ["olio", "acrilico", "acquerello"], "indice_tintoriale": 9 },
  { "nome": "Perinone Orange PO43", "codice": "PO43", "colore": "#D84808", "tipo": "trasparente", "opacita": 0.30, "k_factor": 1.0, "s_factor": 0.30, "resistenza_luce": "eccellente", "compatibilità": ["olio", "acrilico"], "indice_tintoriale": 9 },
  { "nome": "Pyrrole Orange PO73", "codice": "PO73", "colore": "#E04010", "tipo": "trasparente", "opacita": 0.30, "k_factor": 1.0, "s_factor": 0.25, "resistenza_luce": "eccellente", "compatibilità": ["olio", "acrilico"], "indice_tintoriale": 9 },
  { "nome": "Cadmium Red Light PR108", "codice": "PR108", "colore": "#D42818", "tipo": "opaco", "opacita": 0.95, "k_factor": 1.0, "s_factor": 1.65, "resistenza_luce": "eccellente", "compatibilità": ["olio", "acrilico"], "indice_tintoriale": 6 },
  { "nome": "Cadmium Red Deep PR108", "codice": "PR108b", "colore": "#B01818", "tipo": "opaco", "opacita": 0.95, "k_factor": 1.0, "s_factor": 1.60, "resistenza_luce": "eccellente", "compatibilità": ["olio", "acrilico"], "indice_tintoriale": 6 },
  { "nome": "Pyrrole Scarlet PR255", "codice": "PR255", "colore": "#E02010", "tipo": "trasparente", "opacita": 0.30, "k_factor": 1.0, "s_factor": 0.20, "resistenza_luce": "eccellente", "compatibilità": ["olio", "acrilico"], "indice_tintoriale": 9 },
  { "nome": "Pyrrole Red PR254", "codice": "PR254", "colore": "#C81820", "tipo": "trasparente", "opacita": 0.30, "k_factor": 1.0, "s_factor": 0.20, "resistenza_luce": "eccellente", "compatibilità": ["olio", "acrilico"], "indice_tintoriale": 9 },
  { "nome": "Naphthol Red PR112", "codice": "PR112", "colore": "#B82028", "tipo": "semicoprente", "opacita": 0.70, "k_factor": 1.0, "s_factor": 0.50, "resistenza_luce": "modesta", "compatibilità": ["acrilico", "acquerello"], "indice_tintoriale": 8 },
  { "nome": "Naphthol Red PR188", "codice": "PR188", "colore": "#C02020", "tipo": "semicoprente", "opacita": 0.70, "k_factor": 1.0, "s_factor": 0.50, "resistenza_luce": "modesta", "compatibilità": ["acrilico"], "indice_tintoriale": 8 },
  { "nome": "Alizarin Crimson PR83", "codice": "PR83", "colore": "#851828", "tipo": "trasparente", "opacita": 0.25, "k_factor": 0.4, "s_factor": 0.30, "resistenza_luce": "scarsa", "compatibilità": ["olio", "acquerello"], "indice_tintoriale": 7 },
  { "nome": "Quinacridone Maroon PR206", "codice": "PR206", "colore": "#852030", "tipo": "trasparente", "opacita": 0.30, "k_factor": 1.0, "s_factor": 0.25, "resistenza_luce": "eccellente", "compatibilità": ["olio", "acrilico", "acquerello"], "indice_tintoriale": 9 },
  { "nome": "Quinacridone Red PR209", "codice": "PR209", "colore": "#A02028", "tipo": "trasparente", "opacita": 0.30, "k_factor": 1.0, "s_factor": 0.25, "resistenza_luce": "eccellente", "compatibilità": ["olio", "acrilico", "acquerello"], "indice_tintoriale": 9 },
  { "nome": "Perylene Maroon PR179", "codice": "PR179", "colore": "#6B1828", "tipo": "trasparente", "opacita": 0.30, "k_factor": 0.6, "s_factor": 0.30, "resistenza_luce": "eccellente", "compatibilità": ["olio", "acrilico"], "indice_tintoriale": 8 },
  { "nome": "Indian Red PR101", "codice": "PR101", "colore": "#A05048", "tipo": "opaco", "opacita": 0.90, "k_factor": 1.0, "s_factor": 1.50, "resistenza_luce": "eccellente", "compatibilità": ["olio", "acrilico", "acquerello"], "indice_tintoriale": 4 },
  { "nome": "Venetian Red PR101", "codice": "PR101b", "colore": "#A03828", "tipo": "opaco", "opacita": 0.88, "k_factor": 1.0, "s_factor": 1.40, "resistenza_luce": "eccellente", "compatibilità": ["olio", "acrilico"], "indice_tintoriale": 5 },
  { "nome": "Benzimida Maroon PR171", "codice": "PR171", "colore": "#701838", "tipo": "trasparente", "opacita": 0.35, "k_factor": 0.6, "s_factor": 0.40, "resistenza_luce": "buona", "compatibilità": ["acrilico"], "indice_tintoriale": 7 },
  { "nome": "Cadmium Scarlet PR108", "codice": "PR108c", "colore": "#D01018", "tipo": "opaco", "opacita": 0.95, "k_factor": 1.0, "s_factor": 1.65, "resistenza_luce": "eccellente", "compatibilità": ["olio", "acrilico"], "indice_tintoriale": 6 },
  { "nome": "Quinacridone Rose PV19", "codice": "PV19", "colore": "#D82858", "tipo": "trasparente", "opacita": 0.30, "k_factor": 1.0, "s_factor": 0.20, "resistenza_luce": "eccellente", "compatibilità": ["olio", "acrilico", "acquerello"], "indice_tintoriale": 9 },
  { "nome": "Quinacridone Magenta PV19", "codice": "PV19b", "colore": "#B01850", "tipo": "trasparente", "opacita": 0.30, "k_factor": 1.0, "s_factor": 0.20, "resistenza_luce": "eccellente", "compatibilità": ["acrilico", "acquerello"], "indice_tintoriale": 9 },
  { "nome": "Thioindigo Violet PR88", "codice": "PR88", "colore": "#881878", "tipo": "trasparente", "opacita": 0.30, "k_factor": 1.0, "s_factor": 0.30, "resistenza_luce": "buona", "compatibilità": ["olio", "acrilico"], "indice_tintoriale": 7 },
  { "nome": "Dioxazine Violet PV23", "codice": "PV23", "colore": "#381870", "tipo": "trasparente", "opacita": 0.25, "k_factor": 0.4, "s_factor": 0.15, "resistenza_luce": "eccellente", "compatibilità": ["olio", "acrilico", "acquerello"], "indice_tintoriale": 10 },
  { "nome": "Ultramarine Violet PV15", "codice": "PV15", "colore": "#7848A8", "tipo": "semitrasparente", "opacita": 0.55, "k_factor": 0.8, "s_factor": 0.80, "resistenza_luce": "eccellente", "compatibilità": ["olio", "acrilico", "acquerello"], "indice_tintoriale": 8 },
  { "nome": "Manganese Violet PV16", "codice": "PV16", "colore": "#A050A8", "tipo": "opaco", "opacita": 0.85, "k_factor": 1.0, "s_factor": 1.30, "resistenza_luce": "buona", "compatibilità": ["olio", "acrilico"], "indice_tintoriale": 5 },
  { "nome": "Cobalt Violet PV49", "codice": "PV49", "colore": "#9030B0", "tipo": "opaco", "opacita": 0.85, "k_factor": 1.0, "s_factor": 1.40, "resistenza_luce": "eccellente", "compatibilità": ["olio", "acrilico"], "indice_tintoriale": 6 },
  { "nome": "Ultramarine Blue PB29", "codice": "PB29", "colore": "#2030B0", "tipo": "semitrasparente", "opacita": 0.55, "k_factor": 0.6, "s_factor": 0.70, "resistenza_luce": "eccellente", "compatibilità": ["olio", "acrilico", "acquerello"], "indice_tintoriale": 8 },
  { "nome": "Indanthrone Blue PB60", "codice": "PB60", "colore": "#102060", "tipo": "trasparente", "opacita": 0.30, "k_factor": 0.2, "s_factor": 0.20, "resistenza_luce": "eccellente", "compatibilità": ["olio", "acrilico", "acquerello"], "indice_tintoriale": 10 },
  { "nome": "Phthalo Blue RS PB15:1", "codice": "PB15:1", "colore": "#103888", "tipo": "trasparente", "opacita": 0.25, "k_factor": 0.15, "s_factor": 0.15, "resistenza_luce": "eccellente", "compatibilità": ["olio", "acrilico", "acquerello"], "indice_tintoriale": 10 },
  { "nome": "Phthalo Blue GS PB15:3", "codice": "PB15:3", "colore": "#082870", "tipo": "trasparente", "opacita": 0.25, "k_factor": 0.15, "s_factor": 0.15, "resistenza_luce": "eccellente", "compatibilità": ["olio", "acrilico", "acquerello"], "indice_tintoriale": 10 },
  { "nome": "Manganese Blue PB33", "codice": "PB33", "colore": "#38B8D0", "tipo": "semitrasparente", "opacita": 0.50, "k_factor": 0.8, "s_factor": 0.70, "resistenza_luce": "modesta", "compatibilità": ["olio", "acrilico"], "indice_tintoriale": 7 },
  { "nome": "Prussian Blue PB27", "codice": "PB27", "colore": "#102040", "tipo": "semitrasparente", "opacita": 0.50, "k_factor": 0.2, "s_factor": 0.50, "resistenza_luce": "modesta", "compatibilità": ["olio", "acrilico", "acquerello"], "indice_tintoriale": 9 },
  { "nome": "Cobalt Blue PB28", "codice": "PB28", "colore": "#3858C8", "tipo": "opaco", "opacita": 0.88, "k_factor": 0.5, "s_factor": 1.20, "resistenza_luce": "eccellente", "compatibilità": ["olio", "acrilico"], "indice_tintoriale": 6 },
  { "nome": "Cobalt Blue Deep PB72", "codice": "PB72", "colore": "#2848A8", "tipo": "opaco", "opacita": 0.88, "k_factor": 0.5, "s_factor": 1.20, "resistenza_luce": "eccellente", "compatibilità": ["olio", "acrilico"], "indice_tintoriale": 6 },
  { "nome": "Cerulean Blue PB35", "codice": "PB35", "colore": "#5888D8", "tipo": "opaco", "opacita": 0.90, "k_factor": 0.6, "s_factor": 1.50, "resistenza_luce": "eccellente", "compatibilità": ["olio", "acrilico"], "indice_tintoriale": 5 },
  { "nome": "Cerulean Blue Hue PB36", "codice": "PB36", "colore": "#4878C8", "tipo": "opaco", "opacita": 0.90, "k_factor": 0.6, "s_factor": 1.40, "resistenza_luce": "eccellente", "compatibilità": ["olio", "acrilico"], "indice_tintoriale": 6 },
  { "nome": "Turquoise Blue PB16", "codice": "PB16", "colore": "#18A8B8", "tipo": "trasparente", "opacita": 0.25, "k_factor": 0.5, "s_factor": 0.30, "resistenza_luce": "eccellente", "compatibilità": ["olio", "acrilico", "acquerello"], "indice_tintoriale": 9 },
  { "nome": "Phthalo Turquoise PB16", "codice": "PB16b", "colore": "#00A0B0", "tipo": "trasparente", "opacita": 0.25, "k_factor": 0.4, "s_factor": 0.25, "resistenza_luce": "eccellente", "compatibilità": ["olio", "acrilico", "acquerello"], "indice_tintoriale": 10 },
  { "nome": "Cobalt Turquoise PB36", "codice": "PB36b", "colore": "#28A8B0", "tipo": "opaco", "opacita": 0.88, "k_factor": 0.7, "s_factor": 1.30, "resistenza_luce": "eccellente", "compatibilità": ["olio", "acrilico"], "indice_tintoriale": 6 },
  { "nome": "Viridian PG18", "codice": "PG18", "colore": "#208058", "tipo": "trasparente", "opacita": 0.35, "k_factor": 0.3, "s_factor": 0.35, "resistenza_luce": "eccellente", "compatibilità": ["olio", "acrilico", "acquerello"], "indice_tintoriale": 7 },
  { "nome": "Phthalo Green PG7", "codice": "PG7", "colore": "#005830", "tipo": "trasparente", "opacita": 0.25, "k_factor": 0.15, "s_factor": 0.15, "resistenza_luce": "eccellente", "compatibilità": ["olio", "acrilico", "acquerello"], "indice_tintoriale": 10 },
  { "nome": "Permanent Green Deep PG7", "codice": "PG7b", "colore": "#186840", "tipo": "trasparente", "opacita": 0.30, "k_factor": 0.4, "s_factor": 0.30, "resistenza_luce": "eccellente", "compatibilità": ["olio", "acrilico"], "indice_tintoriale": 9 },
  { "nome": "Permanent Green Light PG50", "codice": "PG50", "colore": "#28A050", "tipo": "trasparente", "opacita": 0.35, "k_factor": 0.7, "s_factor": 0.40, "resistenza_luce": "buona", "compatibilità": ["acrilico", "acquerello"], "indice_tintoriale": 8 },
  { "nome": "Chromium Oxide Green PG17", "codice": "PG17", "colore": "#488838", "tipo": "opaco", "opacita": 0.92, "k_factor": 0.5, "s_factor": 1.50, "resistenza_luce": "eccellente", "compatibilità": ["olio", "acrilico", "acquerello"], "indice_tintoriale": 4 },
  { "nome": "Hooker's Green PG7", "codice": "PG7c", "colore": "#286038", "tipo": "trasparente", "opacita": 0.35, "k_factor": 0.8, "s_factor": 0.50, "resistenza_luce": "buona", "compatibilità": ["acquerello"], "indice_tintoriale": 6 },
  { "nome": "Sap Green PG36", "codice": "PG36", "colore": "#487830", "tipo": "trasparente", "opacita": 0.35, "k_factor": 0.8, "s_factor": 0.60, "resistenza_luce": "modesta", "compatibilità": ["acquerello"], "indice_tintoriale": 5 },
  { "nome": "Permanent Green Yellowish PG36", "codice": "PG36b", "colore": "#88B828", "tipo": "trasparente", "opacita": 0.35, "k_factor": 0.9, "s_factor": 0.40, "resistenza_luce": "buona", "compatibilità": ["acrilico", "acquerello"], "indice_tintoriale": 7 },
  { "nome": "Phthalo Yellow Green PY151", "codice": "PY151b", "colore": "#98C828", "tipo": "trasparente", "opacita": 0.30, "k_factor": 0.8, "s_factor": 0.40, "resistenza_luce": "buona", "compatibilità": ["acrilico", "acquerello"], "indice_tintoriale": 8 },
  { "nome": "Raw Sienna PBr7", "codice": "PBr7", "colore": "#8C5E20", "tipo": "trasparente", "opacita": 0.40, "k_factor": 1.0, "s_factor": 0.90, "resistenza_luce": "eccellente", "compatibilità": ["olio", "acrilico", "acquerello"], "indice_tintoriale": 4 },
  { "nome": "Burnt Sienna PBr7", "codice": "PBr7b", "colore": "#7D3A15", "tipo": "trasparente", "opacita": 0.40, "k_factor": 0.8, "s_factor": 0.80, "resistenza_luce": "eccellente", "compatibilità": ["olio", "acrilico", "acquerello"], "indice_tintoriale": 5 },
  { "nome": "Raw Umber PBr7", "codice": "PBr7c", "colore": "#6B4A20", "tipo": "trasparente", "opacita": 0.40, "k_factor": 0.7, "s_factor": 0.90, "resistenza_luce": "eccellente", "compatibilità": ["olio", "acrilico", "acquerello"], "indice_tintoriale": 4 },
  { "nome": "Burnt Umber PBr7", "codice": "PBr7d", "colore": "#5A3218", "tipo": "trasparente", "opacita": 0.40, "k_factor": 0.6, "s_factor": 0.80, "resistenza_luce": "eccellente", "compatibilità": ["olio", "acrilico", "acquerello"], "indice_tintoriale": 5 },
  { "nome": "Titanium White PW6", "codice": "PW6", "colore": "#FAF8F0", "tipo": "opaco", "opacita": 0.98, "k_factor": 1.0, "s_factor": 5.00, "resistenza_luce": "eccellente", "compatibilità": ["olio", "acrilico"], "indice_tintoriale": 2 },
  { "nome": "Lamp Black PBk6", "codice": "PBk6", "colore": "#0B0B0B", "tipo": "trasparente", "opacita": 0.45, "k_factor": 0.95, "s_factor": 0.40, "resistenza_luce": "eccellente", "compatibilità": ["olio", "acrilico", "acquerello"], "indice_tintoriale": 9 },
  { "nome": "Ivory Black PBk9", "codice": "PBk9", "colore": "#100E08", "tipo": "semicoprente", "opacita": 0.70, "k_factor": 0.9, "s_factor": 1.00, "resistenza_luce": "eccellente", "compatibilità": ["olio", "acrilico", "acquerello"], "indice_tintoriale": 3 },
  { "nome": "Mars Black PBk11", "codice": "PBk11", "colore": "#080808", "tipo": "opaco", "opacita": 0.98, "k_factor": 0.9, "s_factor": 1.20, "resistenza_luce": "eccellente", "compatibilità": ["olio", "acrilico"], "indice_tintoriale": 4 },
  { "nome": "Perylene Black PBk31", "codice": "PBk31", "colore": "#0A0A10", "tipo": "trasparente", "opacita": 0.50, "k_factor": 0.8, "s_factor": 0.50, "resistenza_luce": "eccellente", "compatibilità": ["olio", "acrilico"], "indice_tintoriale": 8 },
  { "nome": "Grigio Titanio Chiaro", "codice": "MIX1", "colore": "#D0D0D0", "tipo": "opaco", "opacita": 0.92, "k_factor": 1.0, "s_factor": 4.50, "resistenza_luce": "eccellente", "compatibilità": ["olio", "acrilico", "acquerello"], "indice_tintoriale": 2 },
  { "nome": "Grigio Argento", "codice": "MIX2", "colore": "#B8B8B8", "tipo": "opaco", "opacita": 0.90, "k_factor": 1.0, "s_factor": 4.00, "resistenza_luce": "eccellente", "compatibilità": ["olio", "acrilico"], "indice_tintoriale": 3 },
  { "nome": "Grigio Cenere", "codice": "MIX3", "colore": "#A0A0A0", "tipo": "opaco", "opacita": 0.88, "k_factor": 1.0, "s_factor": 3.50, "resistenza_luce": "eccellente", "compatibilità": ["olio", "acrilico"], "indice_tintoriale": 4 },
  { "nome": "Grigio Neutro Medio", "codice": "MIX4", "colore": "#888888", "tipo": "opaco", "opacita": 0.88, "k_factor": 1.0, "s_factor": 3.00, "resistenza_luce": "eccellente", "compatibilità": ["olio", "acrilico", "acquerello"], "indice_tintoriale": 4 },
  { "nome": "Grigio di Davy", "codice": "MIX5", "colore": "#606068", "tipo": "semicoprente", "opacita": 0.65, "k_factor": 0.9, "s_factor": 2.00, "resistenza_luce": "buona", "compatibilità": ["olio", "acrilico", "acquerello"], "indice_tintoriale": 5 },
  { "nome": "Grigio Freddo", "codice": "MIX6", "colore": "#585868", "tipo": "opaco", "opacita": 0.88, "k_factor": 0.9, "s_factor": 2.50, "resistenza_luce": "eccellente", "compatibilità": ["olio", "acrilico"], "indice_tintoriale": 5 },
  { "nome": "Grigio Caldo", "codice": "MIX7", "colore": "#685850", "tipo": "opaco", "opacita": 0.88, "k_factor": 0.9, "s_factor": 2.40, "resistenza_luce": "eccellente", "compatibilità": ["olio", "acrilico"], "indice_tintoriale": 5 },
  { "nome": "Grigio Ardesia", "codice": "MIX8", "colore": "#485058", "tipo": "semicoprente", "opacita": 0.70, "k_factor": 0.7, "s_factor": 1.80, "resistenza_luce": "eccellente", "compatibilità": ["olio", "acrilico", "acquerello"], "indice_tintoriale": 6 },
  { "nome": "Grigio di Payne", "codice": "MIX9", "colore": "#384050", "tipo": "semitrasparente", "opacita": 0.55, "k_factor": 0.5, "s_factor": 1.20, "resistenza_luce": "buona", "compatibilità": ["olio", "acrilico", "acquerello"], "indice_tintoriale": 7 },
  { "nome": "Grigio Carbone", "codice": "MIX10", "colore": "#1A1A1A", "tipo": "semicoprente", "opacita": 0.85, "k_factor": 0.3, "s_factor": 1.50, "resistenza_luce": "eccellente", "compatibilità": ["olio", "acrilico", "acquerello"], "indice_tintoriale": 8 }
]